{
    "versao": "v29",
    "data": "2026-01-24 20:48:07",
    "tipo_problema": "regressao",
    "melhor_modelo": "GradientBoosting",
    "melhor_score": 0.8554627150469146,
    "metricas": {
        "RandomForest": 0.8349497169888082,
        "ExtraTrees": 0.8199015642882582,
        "GradientBoosting": 0.8554627150469146,
        "LinearRegression": 0.7459305254811328,
        "Ridge": 0.7459395411307879,
        "Lasso": 0.7459512222414171,
        "SVR": -0.10255883513733174,
        "KNN": 0.6826080781286608,
        "DecisionTree": 0.6969469036839298
    },
    "dataset_shape": [
        1338,
        7
    ],
    "colunas": [
        "age",
        "sex",
        "bmi",
        "children",
        "smoker",
        "region",
        "charges"
    ],
    "arquivo_dataset": "dataset.csv",
    "comentario": ""
}